setup.py
fumi_probability/Binomialdistribution.py
fumi_probability/Gaussiandistribution.py
fumi_probability/Generaldistribution.py
fumi_probability/__init__.py
fumi_probability.egg-info/PKG-INFO
fumi_probability.egg-info/SOURCES.txt
fumi_probability.egg-info/dependency_links.txt
fumi_probability.egg-info/not-zip-safe
fumi_probability.egg-info/top_level.txt