Metadata-Version: 2.1
Name: fumi-probability
Version: 0.2
Summary: Gaussian and Binomial distributions
Author: Fumihiro Nakashima
Author-email: fuminaka387@gmail.com
